madc/__init__.py
madc/app_settings.py
madc/apps.py
madc/auth_hooks.py
madc/decorators.py
madc/forms.py
madc/providers.py
madc/tasks.py
madc/urls.py
madc/views.py
madc/api/__init__.py
madc/api/helpers.py
madc/api/schema.py
madc/api/admin/__init__.py
madc/api/admin/admin.py
madc/api/skill/__init__.py
madc/api/skill/skillchecker.py
madc/helpers/__init__.py
madc/helpers/skill_handler.py
madc/images/admin.png
madc/images/characters.png
madc/images/doctrine.png
madc/images/missing.png
madc/locale/django.pot
madc/locale/cs_CZ/LC_MESSAGES/django.po
madc/locale/de/LC_MESSAGES/django.mo
madc/locale/de/LC_MESSAGES/django.po
madc/locale/en/LC_MESSAGES/django.po
madc/locale/es/LC_MESSAGES/django.po
madc/locale/fr_FR/LC_MESSAGES/django.po
madc/locale/it_IT/LC_MESSAGES/django.po
madc/locale/ja/LC_MESSAGES/django.po
madc/locale/ko_KR/LC_MESSAGES/django.po
madc/locale/nl_NL/LC_MESSAGES/django.po
madc/locale/pl_PL/LC_MESSAGES/django.po
madc/locale/ru/LC_MESSAGES/django.po
madc/locale/sk/LC_MESSAGES/django.po
madc/locale/uk/LC_MESSAGES/django.po
madc/locale/zh_Hans/LC_MESSAGES/django.po
madc/managers/__init__.py
madc/managers/skilllist_manager.py
madc/migrations/0001_initial.py
madc/migrations/0002_alter_general_options.py
madc/migrations/0003_alter_skilllist_options.py
madc/migrations/0004_alter_skilllist_category_alter_skilllist_name.py
madc/migrations/__init__.py
madc/models/__init__.py
madc/models/general.py
madc/models/skillchecker.py
madc/static/madc/css/progress.css
madc/static/madc/images/Spinner-1s-64px-dark.gif
madc/static/madc/images/Spinner-1s-64px-light.gif
madc/static/madc/images/clear.png
madc/static/madc/images/loading.gif
madc/static/madc/js/corporation-checker.js
madc/static/madc/js/manage.js
madc/static/madc/js/modal-system.js
madc/static/madc/js/skill-checker.js
madc/static/madc/js/skill-system.js
madc/static/madc/js/modals/skilllist-delete.js
madc/static/madc/libs/x-editable/1.5.8/css/bootstrap-editable.css
madc/static/madc/libs/x-editable/1.5.8/img/clear.png
aa_memberaudit_dc-0.3.3.dist-info/METADATA
aa_memberaudit_dc-0.3.3.dist-info/WHEEL
aa_memberaudit_dc-0.3.3.dist-info/licenses/LICENSE
aa_memberaudit_dc-0.3.3.dist-info/RECORD
